yt_spam_purge/__init__.py
yt_spam_purge/__main__.py
yt_spam_purge/assets/SpamAccountsList.txt
yt_spam_purge/assets/SpamDomainsList.txt
yt_spam_purge/assets/SpamThreadsList.txt
yt_spam_purge/assets/SpamVersionInfo.json
yt_spam_purge/assets/cancelButton.png
yt_spam_purge/assets/default_config.ini
yt_spam_purge/assets/executeButton.png
yt_spam_purge/assets/icon.png
yt_spam_purge/assets/inputSubmitButton.png
yt_spam_purge/assets/inputTextBox.png
yt_spam_purge/assets/outputTextBox.png
yt_spam_purge/assets/rootZoneDomainList.txt
yt_spam_purge/auth.py
yt_spam_purge/cli.py
yt_spam_purge/community_downloader.py
yt_spam_purge/files.py
yt_spam_purge/gui.py
yt_spam_purge/logging.py
yt_spam_purge/operations.py
yt_spam_purge/prepare_modes.py
yt_spam_purge/shared_imports.py
yt_spam_purge/utils.py
yt_spam_purge/validation.py
yt_spam_purge-3.0.0a4.dist-info/entry_points.txt
yt_spam_purge-3.0.0a4.dist-info/LICENSE
yt_spam_purge-3.0.0a4.dist-info/WHEEL
yt_spam_purge-3.0.0a4.dist-info/METADATA
yt_spam_purge-3.0.0a4.dist-info/RECORD
