Metadata-Version: 2.1
Name: yt-spam-purge
Version: 3.0.0a4
Summary: Easily scan for and delete scam comments on your YouTube channel.
Home-page: https://github.com/ThioJoe/YT-Spammer-Purge
License: GNU General Public License v3.0
Author: ThioJoe
Author-email: joe@thiojoe.com
Requires-Python: >=3.10,<4.0
Classifier: License :: Other/Proprietary License
Classifier: Programming Language :: Python :: 3
Classifier: Programming Language :: Python :: 3.10
Requires-Dist: anyio (>=3.5.0,<4.0.0)
Requires-Dist: confusables (>=1.2.0,<2.0.0)
Requires-Dist: google-api-python-client (>=2.36.0,<3.0.0)
Requires-Dist: google-auth-oauthlib (>=0.4.6,<0.5.0)
Requires-Dist: python-Levenshtein (>=0.12.2,<0.13.0)
Requires-Dist: rich (>=11.1.0,<12.0.0)
Requires-Dist: rtfunicode (>=2.0,<3.0)
Requires-Dist: tld (>=0.12.6,<0.13.0)
Requires-Dist: trio (>=0.19.0,<0.20.0)
Requires-Dist: typer (>=0.4.0,<0.5.0)
Project-URL: Repository, https://github.com/dekoza/yt-spam-purge
